django_async_extensions/__init__.py
django_async_extensions/contrib/__init__.py
django_async_extensions/contrib/auth/__init__.py
django_async_extensions/contrib/auth/mixins.py
django_async_extensions/core/__init__.py
django_async_extensions/core/paginator.py
django_async_extensions/forms/__init__.py
django_async_extensions/forms/models.py
django_async_extensions/forms/utils.py
django_async_extensions/middleware/__init__.py
django_async_extensions/middleware/base.py
django_async_extensions/utils/__init__.py
django_async_extensions/utils/decorators.py
django_async_extensions/views/__init__.py
django_async_extensions/views/generic/__init__.py
django_async_extensions/views/generic/base.py
django_async_extensions/views/generic/dates.py
django_async_extensions/views/generic/detail.py
django_async_extensions/views/generic/edit.py
django_async_extensions/views/generic/list.py
django_async_extensions-0.0.5.dist-info/LICENSE
django_async_extensions-0.0.5.dist-info/METADATA
django_async_extensions-0.0.5.dist-info/WHEEL
django_async_extensions-0.0.5.dist-info/RECORD
