Metadata-Version: 2.3
Name: django-async-extensions
Version: 0.0.5
Summary: provide async capable stuff for django
License: MIT
Author: amirreza
Author-email: amir.rsf1380@gmail.com
Requires-Python: >=3.10
Classifier: Programming Language :: Python
Classifier: Environment :: Web Environment
Classifier: Development Status :: 4 - Beta
Classifier: Topic :: Utilities
Classifier: Intended Audience :: Developers
Classifier: License :: OSI Approved :: BSD License
Classifier: Operating System :: OS Independent
Classifier: Topic :: Software Development :: Libraries
Classifier: Programming Language :: Python :: 3
Classifier: Programming Language :: Python :: 3 :: Only
Classifier: Programming Language :: Python :: 3.10
Classifier: Programming Language :: Python :: 3.11
Classifier: Programming Language :: Python :: 3.12
Classifier: Programming Language :: Python :: 3.13
Classifier: Framework :: Django :: 4.2
Classifier: Framework :: Django :: 5.0
Classifier: Framework :: Django :: 5.1
Classifier: Framework :: Django :: 5.2
Classifier: Framework :: AsyncIO
Requires-Dist: django (>=4.2)
Project-URL: Documentation, https://django-async-extensions.readthedocs.io/en/latest/
Project-URL: Homepage, https://github.com/django-utils/django-async-extensions
Project-URL: Issues, https://github.com/django-utils/django-async-extensions/issues
Project-URL: Source, https://github.com/django-utils/django-async-extensions
